imgfind/__init__.py
imgfind/__main__.py
imgfind/find/__init__.py
imgfind/find/__main__.py
imgfind/find/actions.py
imgfind/find/main.py
imgfind/find/options.py
imgfind/lib/__init__.py
imgfind/lib/exif.py
imgfind/lib/ffmpeg.py
imgfind/lib/graphicsmagick.py
imgfind/lib/imagemagick.py
imgfind/lib/libvips.py
imgfind/lib/pillow.py
imgfind/teeny/__init__.py
imgfind/teeny/__main__.py
imgfind/teeny/main.py
imgfind/teeny/options.py
imgfind/vfind/__init__.py
imgfind/vfind/__main__.py
imgfind/vfind/main.py
imgfind/vfind/options.py
imgfind/vteeny/__init__.py
imgfind/vteeny/__main__.py
imgfind/vteeny/main.py
imgfind/vteeny/options.py
imgfind-0.3.5.data/data/share/bash-completion/completions/ifind
imgfind-0.3.5.data/data/share/bash-completion/completions/teeny
imgfind-0.3.5.data/data/share/bash-completion/completions/vfind
imgfind-0.3.5.data/data/share/fish/vendor_completions.d/ifind.fish
imgfind-0.3.5.data/data/share/fish/vendor_completions.d/teeny.fish
imgfind-0.3.5.data/data/share/fish/vendor_completions.d/vfind.fish
imgfind-0.3.5.data/data/share/zsh/site-functions/_ifind
imgfind-0.3.5.data/data/share/zsh/site-functions/_teeny
imgfind-0.3.5.data/data/share/zsh/site-functions/_vfind
imgfind-0.3.5.dist-info/METADATA
imgfind-0.3.5.dist-info/WHEEL
imgfind-0.3.5.dist-info/entry_points.txt
imgfind-0.3.5.dist-info/top_level.txt
imgfind-0.3.5.dist-info/RECORD
