Metadata-Version: 2.4
Name: imgfind
Version: 0.3.5
Summary: Find and modify images in a directory, similar to findutils
Requires-Python: >=3.5
Requires-Dist: Pillow
Requires-Dist: piexif
Provides-Extra: libvips
Requires-Dist: pyvips; extra == "libvips"
Dynamic: description
Dynamic: description-content-type
